loopr/__init__.py
loopr/api/__init__.py
loopr/api/annotation/__init__.py
loopr/api/annotation/annotation.py
loopr/api/dataset/__init__.py
loopr/api/dataset/abs_dataset.py
loopr/api/dataset/dataset.py
loopr/api/dataset/image_dataset.py
loopr/api/dataset/paired_dataset.py
loopr/api/project/__init__.py
loopr/api/project/abs_project.py
loopr/api/project/categorization_project.py
loopr/api/project/object_detection_project.py
loopr/api/project/project.py
loopr/api/project/relevancy_project.py
loopr/api/row/__init__.py
loopr/api/row/abs_row.py
loopr/api/row/image_row.py
loopr/api/row/paired_row.py
loopr/api/row/row.py
loopr/client.py
loopr/exceptions.py
loopr/models/__init__.py
loopr/models/entities/__init__.py
loopr/models/entities/data_types.py
loopr/models/entities/loopr_enitity.py
loopr/models/entities/loopr_object.py
loopr/models/entities/loopr_object_collection.py
loopr/resources/__init__.py
loopr/resources/constants.py
loopr/utils/__init__.py
loopr/utils/common_utils.py
loopr/utils/response_handler.py
loopr/utils/retry.py
loopr-0.1.0.dist-info/LICENSE
loopr-0.1.0.dist-info/WHEEL
loopr-0.1.0.dist-info/METADATA
loopr-0.1.0.dist-info/RECORD
