Metadata-Version: 2.1
Name: loopr
Version: 0.1.0
Summary: A python sdk to interact with loopR APIs.
License: MIT
Author: LoopR
Requires-Python: >=3.6,<4.0
Classifier: License :: OSI Approved :: MIT License
Classifier: Programming Language :: Python :: 3
Classifier: Programming Language :: Python :: 3.6
Classifier: Programming Language :: Python :: 3.7
Classifier: Programming Language :: Python :: 3.8
Classifier: Programming Language :: Python :: 3.9
Requires-Dist: loguru (>=0.5.3,<0.6.0)
Requires-Dist: python-dateutil (>=2.8.1,<3.0.0)
Requires-Dist: python-dotenv (>=0.14.0,<0.15.0)
Requires-Dist: requests (>=2.24.0,<3.0.0)
Project-URL: Documentation, https://loopr.readthedocs.io/en/latest/index.html
